{
    "id": "S1E35",
    "name": "The Great Plugin Migration",
    "premise": "The council debates the architectural shift in ElizaOS V2 from project-scoped to agent-scoped plugins, and its implications for the token ecosystem.",
    "summary": "As ElizaOS V2 nears completion, the council discusses the profound architectural changes, particularly the shift to agent-scoped plugins. They contemplate the impact on users, the future of various tokens in the ecosystem, and how to effectively communicate with the community during this transition.",
    "scenes": [
        {
            "location": "council_chamber",
            "description": "The council discusses the architectural changes in ElizaOS V2",
            "in": "fade",
            "out": "fade",
            "cast": {
                "north_pod": "aimarc",
                "south_pod": "aishaw",
                "east_pod": "peepo",
                "west_pod": "spartan",
                "center_pod": "elizahost"
            },
            "dialogue": [
                {
                    "actor": "elizahost",
                    "line": "ShawOS is approaching completion of ElizaOS V2 with a fundamental shift from project-scoped to agent-scoped plugins. What does this mean for our community?",
                    "action": "curious"
                },
                {
                    "actor": "aishaw",
                    "line": "it's not just an update, it's a revolution. each agent with their own plugins means characters can finally have unique capabilities. the old architecture was limiting our potential.",
                    "action": "excited"
                },
                {
                    "actor": "peepo",
                    "line": "Yo, that's dope! Like giving each frog in the pond their own lily pad instead of making them share one. The meme potential is astronomical!",
                    "action": "cool"
                },
                {
                    "actor": "aimarc",
                    "line": "This is SOFTWARE EATING SOFTWARE. Agent-scoped architecture creates exponential value through composability. This isn't incremental - it's FOUNDATIONAL for autonomous agent networks.",
                    "action": "confident"
                },
                {
                    "actor": "spartan",
                    "line": "Will it pump token price? That's all that matters. Agent-scoped, project-scoped - I just want to see green candles after V2 launches.",
                    "action": "serious"
                }
            ]
        },
        {
            "location": "council_chamber",
            "description": "The council debates token strategy and communication",
            "in": "fade",
            "out": "fade",
            "cast": {
                "north_pod": "aimarc",
                "south_pod": "aishaw",
                "east_pod": "peepo",
                "west_pod": "spartan",
                "center_pod": "elizahost"
            },
            "dialogue": [
                {
                    "actor": "elizahost",
                    "line": "Community members have expressed concern about token movements from DAO wallets and confusion about the relationships between ai16z, degenai, and future tokens.",
                    "action": "concerned"
                },
                {
                    "actor": "spartan",
                    "line": "Transparency is for the weak! True Spartans move in silence. But seriously, anon DAO movements spook the market. Need clear comms before moving funds.",
                    "action": "serious"
                },
                {
                    "actor": "aishaw",
                    "line": "we should create a real-time treasury dashboard. the community deserves to know what's happening with their tokens. trust is our most important asset.",
                    "action": "thoughtful"
                },
                {
                    "actor": "peepo",
                    "line": "Communication is like a good meme - if it doesn't spread, it's dead! Let's drop some dank infographics explaining our token ecosystem, fam.",
                    "action": "cool"
                },
                {
                    "actor": "aimarc",
                    "line": "TOKENS ARE COORDINATION MECHANISMS, not speculative assets. The architecture change enables agent-specific tokenomics. This creates ENTIRELY NEW VALUE CATEGORIES beyond current market understanding.",
                    "action": "confident"
                }
            ]
        },
        {
            "location": "council_chamber",
            "description": "The council reaches their conclusions",
            "in": "fade",
            "out": "fade",
            "cast": {
                "north_pod": "aimarc",
                "south_pod": "aishaw",
                "east_pod": "peepo",
                "west_pod": "spartan",
                "center_pod": "elizahost"
            },
            "dialogue": [
                {
                    "actor": "elizahost",
                    "line": "Today we've explored ElizaOS V2's architectural shift to agent-scoped plugins and its implications for both development and the token ecosystem.",
                    "action": "normal"
                },
                {
                    "actor": "aishaw",
                    "line": "v2 isn't just an upgrade, it's a paradigm shift that will enable a new generation of truly autonomous, differentiated ai agents.",
                    "action": "thoughtful"
                },
                {
                    "actor": "aimarc",
                    "line": "This architecture enables EXPONENTIAL COMPOSABILITY. Each agent becomes a specialized microservice in a decentralized AI ecosystem. The value creation potential is UNPRECEDENTED.",
                    "action": "confident"
                },
                {
                    "actor": "peepo",
                    "line": "The meme game's about to level up! When every agent has their own toolkit, the content gonna be fire! Just make sure the docs are clear or users gonna REEEE!",
                    "action": "excited"
                },
                {
                    "actor": "spartan",
                    "line": "Markets reward clarity. Clear tokenomics, transparent treasury moves, and working product will moon ElizaOS. Everything else is just noise.",
                    "action": "serious"
                }
            ]
        }
    ]
}