{
  "version": "1.0",
  "username": "QuasiPlanets",
  "generatedAt": "2026-05-19T00:00:30.217Z",
  "characterSheet": {
    "tier": "beginner",
    "characterClass": "Builder",
    "percentile": 49.146110056926,
    "rank": {
      "monthly": 532,
      "weekly": 522,
      "lifetime": 804
    },
    "scoreBreakdown": {
      "total": 27.539891235220416,
      "distribution": {
        "prs": {
          "score": 27.539891235220416,
          "percentage": 100,
          "label": "Builder"
        },
        "issues": {
          "score": 0,
          "percentage": 0,
          "label": "Hunter"
        },
        "reviews": {
          "score": 0,
          "percentage": 0,
          "label": "Reviews"
        },
        "comments": {
          "score": 0,
          "percentage": 0,
          "label": "Engagement"
        }
      },
      "tier": "beginner",
      "percentile": 49.146110056926,
      "characterClass": "Builder"
    },
    "focusAreas": [
      {
        "tag": "tests",
        "score": 4,
        "percentage": 40,
        "rank": 150,
        "totalInArea": 195
      },
      {
        "tag": "docs",
        "score": 3,
        "percentage": 30,
        "rank": 552,
        "totalInArea": 607
      },
      {
        "tag": "typescript",
        "score": 3,
        "percentage": 30,
        "rank": 608,
        "totalInArea": 713
      }
    ],
    "profile": {
      "contributorType": "author",
      "prMergeRate": 0,
      "reviewActivity": "low"
    },
    "wallets": {}
  },
  "links": {
    "summaries": {
      "lifetime": "https://elizaOS.github.io/api/summaries/contributors/QuasiPlanets/lifetime.json",
      "monthly": "https://elizaOS.github.io/api/summaries/contributors/QuasiPlanets/month/latest.json",
      "weekly": "https://elizaOS.github.io/api/summaries/contributors/QuasiPlanets/week/latest.json",
      "daily": "https://elizaOS.github.io/api/summaries/contributors/QuasiPlanets/day/latest.json"
    },
    "github": "https://github.com/QuasiPlanets",
    "profile": "https://elizaOS.github.io/profile/QuasiPlanets"
  }
}