{
  "version": "1.0",
  "username": "imholders",
  "generatedAt": "2026-01-28T23:18:39.512Z",
  "characterSheet": {
    "tier": "active",
    "characterClass": "Scribe",
    "percentile": 96.46814404432132,
    "rank": {
      "monthly": 1239,
      "weekly": 1224,
      "lifetime": 51
    },
    "scoreBreakdown": {
      "total": 313.6281229204402,
      "distribution": {
        "prs": {
          "score": 313.6281229204402,
          "percentage": 100,
          "label": "Builder"
        },
        "issues": {
          "score": 0,
          "percentage": 0,
          "label": "Hunter"
        },
        "reviews": {
          "score": 0,
          "percentage": 0,
          "label": "Reviews"
        },
        "comments": {
          "score": 0,
          "percentage": 0,
          "label": "Engagement"
        }
      },
      "tier": "active",
      "percentile": 96.46814404432132,
      "characterClass": "Scribe"
    },
    "focusAreas": [
      {
        "tag": "docs",
        "score": 37.5,
        "percentage": 100,
        "rank": 69,
        "totalInArea": 571
      }
    ],
    "achievements": [
      {
        "type": "pr_master",
        "tier": "beginner",
        "earnedAt": "2025-10-27T23:09:22.333Z"
      }
    ],
    "profile": {
      "contributorType": "author",
      "prMergeRate": 90.9,
      "reviewActivity": "low"
    },
    "wallets": {}
  },
  "links": {
    "summaries": {
      "lifetime": "https://elizaOS.github.io/api/summaries/contributors/imholders/lifetime.json",
      "monthly": "https://elizaOS.github.io/api/summaries/contributors/imholders/month/latest.json",
      "weekly": "https://elizaOS.github.io/api/summaries/contributors/imholders/week/latest.json",
      "daily": "https://elizaOS.github.io/api/summaries/contributors/imholders/day/latest.json"
    },
    "github": "https://github.com/imholders",
    "profile": "https://elizaOS.github.io/profile/imholders"
  }
}