{
  "server": "elizaOS",
  "title": "elizaOS Discord - 2025-11-04",
  "date": 1762214400,
  "stats": {
    "totalMessages": 144,
    "totalUsers": 33
  },
  "categories": [
    {
      "channelId": "1253563209462448241",
      "channelName": "💬-discussion",
      "summary": "# Analysis of 💬-discussion Channel\n\n## 1. Summary\nThe discussion primarily revolves around the upcoming migration of AI16Z tokens to ElizaOS tokens scheduled for November 7th. Users are concerned about how the migration will work, particularly the 1:6 conversion ratio (1 AI16Z token will equal 6 ElizaOS tokens). There's significant confusion about which exchanges will support automatic migration versus requiring manual migration. Kenk, likely a team member, clarified that official information about exchanges supporting automatic migration will be shared on Friday. Users also discussed whether to buy more AI16Z before the migration or wait. Some concerns were raised about project websites not working properly ahead of the migration. Additionally, there was a brief discussion about high APY (35%) on USDC in a related protocol, with warnings about systemic risk exposure to XUSD.\n\n## 2. FAQ\nQ: Can someone explain what will happen to the coins on November 7th? Will they be converted into 6 elizas, and how will this affect the AI16Z exchange rate? (asked by Magistr) A: 1 token ai16z equals 6 tokens ElizaOS (answered by Arceon)\nQ: What is this 1:6 conversion? (asked by Magistr) A: 1 token ai16z equals 6 tokens ElizaOS (answered by Arceon)\nQ: Do we have confirmation on what Hyperliquid is doing? (asked by TOM) A: Unanswered\nQ: How will this be reflected in the price? (asked by Magistr) A: Unanswered\nQ: is this a crypto or an os? (asked by Ashley) A: Unanswered\nQ: Do I buy more ai16z now or wait until the migration (asked by moclov8) A: Unanswered\nQ: can you please tell us what wallets or exchanges will do the migration automatically? (asked by Mohammed S. Abdulmoneem) A: Basically anything not an exchange you'll have to migrate manually. If you don't own the keys it'll be automatic (answered by moclov8)\nQ: So perp can't make automatic swap like spot? (asked by TOM) A: Unanswered\nQ: Why is there a high apy on usdc? 35% is really huge (asked by Smartcat🍣) A: Because they are exposed to systemic risk with xusd... avoid i already have funds trapped due to this (answered by orion)\nQ: Will it be snapshot? (asked by movefree) A: No snapshot. You'll have 90 days to migrate your ai16z (answered by Borko)\n\n## 3. Help Interactions\nHelper: moclov8 | Helpee: Mohammed S. Abdulmoneem | Context: Confusion about which exchanges will handle the token migration automatically | Resolution: Explained that exchanges holding user tokens will handle migration automatically, while self-custody wallets require manual migration\nHelper: Kenk | Helpee: TOM | Context: Confusion about Lighter delisting AI16Z | Resolution: Clarified that Lighter is a perps dex so AI16Z won't be tradable there after migration, and listing ElizaOS is up to them\nHelper: Odilitime | Helpee: cavey65 | Context: User claimed ElizaOS mirror.xyz sites don't work | Resolution: Confirmed that mirror.xyz/elizaos.eth works fine\nHelper: orion | Helpee: Smartcat🍣 | Context: User questioning high APY (35%) on USDC | Resolution: Warned about systemic risk with XUSD and advised to avoid it\nHelper: Borko | Helpee: movefree | Context: Question about whether there will be a snapshot for migration | Resolution: Clarified there's no snapshot and users will have 90 days to migrate their AI16Z\n\n## 4. Action Items\nTechnical: Migration of AI16Z tokens to ElizaOS tokens on November 7th | Description: 1:6 conversion ratio with 90-day migration window | Mentioned By: Multiple users\nDocumentation: List of exchanges supporting automatic migration | Description: Team to share which exchanges will support automatic migration on Friday | Mentioned By: Kenk\nDocumentation: Fix non-working ElizaOS mirror.xyz sites | Description: Some users reporting project announcement sites not working | Mentioned By: cavey65\nTechnical: Address concerns about high APY USDC exposure to XUSD | Description: Users warned about systemic risk with XUSD in lending markets | Mentioned By: orion\nFeature: Launch of 10k Eliza agents | Description: Moca launching 10k Eliza agents | Mentioned By: Reneil",
      "messageCount": 82,
      "userCount": 24
    },
    {
      "channelId": "1300025221834739744",
      "channelName": "💬-coders",
      "summary": "# Discord Chat Analysis for 💬-coders\n\n## 1. Summary:\nThe chat segment contains minimal technical discussion. Jin inquired about Puppeteer/Playwright expertise for headless hardware-accelerated video encoding and streaming in containers. LarpsAI suggested using tools like Nia with MCP to index Puppeteer/Playwright documentation for hybrid search capabilities, supplemented with reference tools like Jina and Exa search synthesis. Rabbidfly mentioned using Playwright for automating banking flows in a proof-of-concept stage and asked about using Clank Tank for scoring student projects in a dev-cursor-UI bootcamp. Orryxis introduced themselves as a Web3 and AI engineer with experience in integrating intelligent agents with decentralized infrastructure.\n\n## 2. FAQ:\nQ: Who is knowledgeable about puppeteer/playwright for headless hardware accelerated video encoding/streaming from inside containers? (asked by jin) A: Partially answered by Rabbidfly who uses Playwright for banking flows but didn't address the container/video aspects\nQ: What are you trying to do [with Playwright]? (asked by Rabbidfly) A: Unanswered\nQ: How usable is clank tank for a simple use case like scoring student capstone projects? (asked by Rabbidfly) A: Unanswered\n\n## 3. Help Interactions:\nHelper: LarpsAI | Helpee: jin | Context: Seeking Puppeteer/Playwright expertise | Resolution: Suggested using Nia with MCP to index documentation and repositories, plus using reference tools for web search synthesis\n\n## 4. Action Items:\nType: Technical | Description: Implement headless hardware accelerated video encoding/streaming from inside containers using Puppeteer/Playwright | Mentioned By: jin\nType: Technical | Description: Evaluate Clank Tank for scoring student capstone projects in dev-cursor-UI bootcamp | Mentioned By: Rabbidfly",
      "messageCount": 11,
      "userCount": 4
    },
    {
      "channelId": "1301363808421543988",
      "channelName": "🥇-partners",
      "summary": "# Discord Channel Analysis: 🥇-partners\n\n## 1. Summary\nThe chat primarily consists of casual discussions rather than technical content. Topics include cryptocurrency investments (particularly Zcash), AI events on platforms like Luma.com, and brief mentions of agent launches. DorianD shared links to AI events on Luma.com, suggesting they could be leveraged for user onboarding and investor presentations. Seppmos discussed their investment in Zcash (ZEC), presenting it as a privacy-focused alternative to Bitcoin with superior technology to Monero. DorianD expressed skepticism about Zcash's privacy claims, suggesting government agencies might have backdoor access. There was a brief mention by Reneil about a \"10k agent launch\" with a link to Twitter/X. The conversation concluded with DorianD commenting on SoundHound's market capitalization and making jokes about \"Elizafy\" as a workforce automation concept. Overall, the discussion lacked substantial technical depth or concrete problem-solving.\n\n## 2. FAQ\nQ: Is Zcash's privacy technology superior to Monero's? (implied by Seppmos) A: DorianD disagreed, suggesting Zcash's key signing ceremonies might be compromised, while drug dealers prefer XMR (Monero)\n\n## 3. Help Interactions\nHelper: None | Helpee: None | Context: No significant help interactions were observed in this chat segment | Resolution: N/A\n\n## 4. Action Items\nType: Feature | Description: Consider engaging with AI events on platforms like Luma.com to onboard users | Mentioned By: DorianD\nType: Feature | Description: Explore creating a dark pool version of HyperLiquid chain for privacy | Mentioned By: DorianD",
      "messageCount": 25,
      "userCount": 3
    },
    {
      "channelId": "1377726087789940836",
      "channelName": "core-devs",
      "summary": "# Discord Chat Analysis - \"core-devs\" Channel\n\n## 1. Summary\nThe chat segment contains minimal technical discussion, primarily focused on brief exchanges about payment configurations for x402 and character files. Odilitime raised a question about where to store payment configurations - either in project initialization (using runtime::registerPaymentConfig) or in character files. Borko and Stan contributed to this discussion, suggesting that if characters can have personal wallets, then x402 configurations could logically be placed in character files. Odilitime confirmed that while environment variables can set defaults, character secrets can override these settings, enabling per-agent wallets. Additionally, there were brief mentions of Elysia (a potential rewrite target), next-generation chips, and some administrative matters like standup invites and a missing cloud channel.\n\n## 2. FAQ\nQ: Where did the cloud channel go? (asked by Borko) A: It's still visible; might be unselected in your client. Check channels and roles. (answered by Odilitime and sam-developer)\nQ: x402 payment configs in project init (with runtime::registerPaymentConfig) OR in character file? (asked by Odilitime) A: If characters can have personal wallets, then configurations can go directly into the character for 402x. (answered by Stan ⚡ and Borko)\nQ: Do chars currently own personal wallets or is it agent/server wide? (asked by Stan ⚡) A: You can use ENV vars to set defaults but can override in character secrets, enabling wallets per agent. (answered by Odilitime)\n\n## 3. Help Interactions\nHelper: sam-developer | Helpee: Borko | Context: Borko couldn't see the cloud channel | Resolution: sam-developer confirmed the channel was visible\nHelper: Odilitime | Helpee: Borko | Context: Missing cloud channel in Discord client | Resolution: Suggested checking if channel was unselected in client settings under \"channels and roles\"\n\n## 4. Action Items\nTechnical: Consider implementing x402 payment configurations in character files | Description: Store payment configs in character files since they can have per-agent wallets | Mentioned By: Odilitime, Stan ⚡, Borko\nTechnical: Evaluate Elysia as potential rewrite target | Description: Consider rewriting to Elysia framework | Mentioned By: cjft\nDocumentation: Document wallet configuration options | Description: Clarify how to set up wallets using ENV vars vs character secrets | Mentioned By: Odilitime",
      "messageCount": 26,
      "userCount": 6
    }
  ]
}