{
  "server": "elizaOS",
  "title": "elizaOS Discord - 2025-09-25",
  "date": 1758758400,
  "stats": {
    "totalMessages": 99,
    "totalUsers": 39
  },
  "categories": [
    {
      "channelId": "1253563209462448241",
      "channelName": "💬-discussion",
      "summary": "# Discord Chat Analysis\n\n## 1. Summary\nThe discussion primarily revolves around the transition of the $ai16z token to $elizaOS. Kenk confirmed this migration and mentioned that detailed instructions would be shared soon. There was discussion about community contribution to elizaOS, with Kenk highlighting existing agents in the server including a daily summary agent and a social sentiment tracker. The possibility of creating a website to showcase these agents was mentioned. A community member named 3on_ proposed creating a community-led AI agent using elizaOS within the Discord server. Samir introduced a project involving a digital twin of the human body that would use the elizaOS leaderboard framework for contribution evaluation. Questions about token migration details dominated the latter part of the conversation, with users seeking clarification about the process, especially for tokens held on exchanges.\n\n## 2. FAQ\nQ: What's Solana? (asked by Homie) A: Solana is a high-speed blockchain known for low transaction costs, often used for DeFi, NFTs, and Web3 apps. (answered by Brinter)\nQ: What's happening with $ai16z? (asked by K4L) A: $ai16z is transitioning to $elizaOS with a migration process that holders will need to follow. Step-by-step details will be shared soon. (answered by Kenk)\nQ: Is there a way for community members to work together to create a community-led AI agent using ELIZA OS? (asked by 3on_.) A: Kenk suggested using the contribution channels to float the idea and find collaborators. (answered by Kenk)\nQ: Is there any way to contribute to elizaos if I'm not technical? (asked by Chase Sommer) A: Yes, you can contribute on the communication side, for example with the French YouTube channel. (answered by Samir)\nQ: Will $ai16z tokens in the 'margin' section on Gate be converted into the new token? (asked by 0xTDL ⚡) A: Unanswered\nQ: Is the new $elizaOS token still on the Solana network? (asked by 0xTDL ⚡) A: The new token is purpose-built for elizaOS v2, for cross-chain operation through Chainlink CCIP, and for agent-native workflows. (answered by Dean)\n\n## 3. Help Interactions\nHelper: Kenk | Helpee: K4L | Context: K4L was seeking information about the future of AI16z tokens | Resolution: Kenk explained that $ai16z is transitioning to $elizaOS and that migration details would be shared soon\nHelper: Kenk | Helpee: 3on_ | Context: 3on_ wanted to know if community members could work together to create an AI agent | Resolution: Kenk provided information about contribution channels and mentioned existing agents in the server\nHelper: Samir | Helpee: Chase Sommer | Context: Chase asked about non-technical contribution opportunities | Resolution: Samir suggested contributing to communications, mentioning the French YouTube channel as an example\n\n## 4. Action Items\nTechnical Tasks: Description: Create a website to showcase elizaOS agents for industry use | Mentioned By: Kenk\nTechnical Tasks: Description: Explore development of an artwork generator agent | Mentioned By: Kenk\nTechnical Tasks: Description: Provide detailed step-by-step migration instructions for $ai16z to $elizaOS | Mentioned By: Kenk\nDocumentation: Description: Share migration process details for $ai16z token holders | Mentioned By: Kenk\nDocumentation: Description: Clarify status of tokens held in exchange margin accounts during migration | Mentioned By: 0xTDL ⚡\nDocumentation: Description: Provide information about the status of other tokens (DegenAI, Eli5) during migration | Mentioned By: Zzzchain\nFeature: Description: Build a digital twin of the human body with elizaOS leaderboard framework for contribution evaluation | Mentioned By: Samir\nFeature: Description: Create a community-led AI agent within the elizaOS Discord | Mentioned By: 3on_\nFeature: Description: Develop an artwork generator agent | Mentioned By: Kenk",
      "messageCount": 65,
      "userCount": 24
    },
    {
      "channelId": "1300025221834739744",
      "channelName": "💬-coders",
      "summary": "# Discord Chat Analysis for 💬-coders Channel\n\n## 1. Summary\nThe chat segment shows minimal technical discussion with a focus on documentation updates and pull requests. Two pull requests were shared: one for general documentation (PR #71) by yung_algorithm and another for the Telegram plugin (PR #15) by orayo to address inconsistencies between documentation and implementation. The conversation also includes networking attempts from blockchain developers looking to collaborate on projects. There were no detailed technical discussions, problem-solving activities, or concrete implementations shared in this segment.\n\n## 2. FAQ\nQ: Any good coder here? (asked by Sirash | DODO CM [Never DM 1st]) A: Unanswered\nQ: Any successful crypto agents created and tested lately? (asked by KrypticNode) A: Unanswered\n\n## 3. Help Interactions\nHelper: orayo | Helpee: Community | Context: Inconsistencies between documentation and implementation in plugin-telegram | Resolution: Created PR #15 to address the issues\n\n## 4. Action Items\nType: Documentation | Description: Review and merge PR #71 for documentation updates | Mentioned By: yung_algorithm\nType: Technical | Description: Review and merge PR #15 for plugin-telegram to fix documentation inconsistencies | Mentioned By: orayo",
      "messageCount": 9,
      "userCount": 7
    },
    {
      "channelId": "1361442528813121556",
      "channelName": "fun",
      "summary": "The chat segment is extremely brief with only two messages. There are no technical discussions, decisions, or problem-solving activities present. The first message from Crispy asks where something was stated by a team, without providing context. The second message from Zzzchain appears to be using a command or emoji reference \"$ELI5<:elizasalute:1304205346885210133>\", possibly requesting a simplified explanation of something, but without sufficient context.",
      "messageCount": 2,
      "userCount": 2
    },
    {
      "channelId": "1301363808421543988",
      "channelName": "🥇-partners",
      "summary": "The chat segment contains no technical discussions, decisions, or problem-solving. It consists only of brief comments from two users discussing their investment in what appears to be a cryptocurrency called \"ai16z\". Rabbidfly mentions buying more of this asset based on personal conviction and research, making jokes about having a crystal ball. DannyNOR NoFapArc briefly comments that the upside potential exceeds the downside risk and mentions hope regarding a \"new token\" that might improve the situation. No technical content, implementations, or concrete solutions are present in this conversation.",
      "messageCount": 9,
      "userCount": 2
    },
    {
      "channelId": "1377726087789940836",
      "channelName": "core-devs",
      "summary": "This chat segment shows minimal technical discussion. The main points were about rescheduling a standup meeting due to team members being in Seoul, and a GitHub repository link for a Twilio plugin that needs to be published. Shaw shared a link to Tanstack, suggesting it might pose a threat to Next.js. There was also a brief mention of someone helping Superteam France use Eliza for their project. Overall, this segment contains mostly casual conversation, links to external content, and coordination about meeting times rather than substantive technical discussions or problem-solving.",
      "messageCount": 14,
      "userCount": 8
    }
  ]
}