{
  "version": "1.0",
  "type": "repository",
  "interval": "day",
  "date": "2026-02-20",
  "generatedAt": "2026-02-20T23:21:14.428Z",
  "sourceLastUpdated": "2026-02-20T23:21:14.428Z",
  "contentFormat": "markdown",
  "contentHash": "b07757dde0d73d52c69217aa0fefb538473776ca2bcedf42a6b686aabaf28246",
  "entity": {
    "repoId": "elizaos-plugins/plugin-n8n-workflow",
    "owner": "elizaos-plugins",
    "repo": "plugin-n8n-workflow"
  },
  "content": "# elizaos-plugins/plugin-n8n-workflow Daily Update (Feb 20, 2026)\n## OVERVIEW \nToday's development focused on addressing a critical issue related to AI node behavior within the n8n workflow plugin, with a new pull request opened to prevent multi-step confabulation and ensure accurate AI node results.\n\n## KEY TECHNICAL DEVELOPMENTS\n\n## NEWLY OPENED PULL REQUESTS\nA new pull request, [#19](https://github.com/elizaos-plugins/plugin-n8n-workflow/pull/19), was opened today. This PR aims to fix an issue where AI nodes might engage in multi-step confabulation and ensures that AI nodes are correctly included in the results.\n\n## CLOSED ISSUES\n\n## NEW ISSUES\n\n## ACTIVE ISSUES"
}