{
  "version": "1.0",
  "type": "contributor",
  "interval": "lifetime",
  "date": "2026-01-11",
  "generatedAt": "2026-01-11T00:56:08.754Z",
  "sourceLastUpdated": "2026-01-11T00:56:08.754Z",
  "contentFormat": "markdown",
  "contentHash": "d1ace406873c9351960e71039771f79b63e5513adae8a2d88d84a0d3874406fc",
  "entity": {
    "username": "JussCubs"
  },
  "content": "# JussCubs\n\n## Activity Ledger\n- **Pull Requests Authored:** 0 merged, 2 open\n- **Pull Requests Reviewed:** 0 total (0 approvals, 0 change requests, 0 comments)\n- **Issues:** 0 opened, 0 closed\n- **Avg Time to Merge:** 0 hours\n\n## Contribution Domains\n- **Documentation:** Updates to plugin-specific documentation within the Eliza framework.\n  - PRs: elizaos/eliza#1707 (docs: update Twitter plugin README), elizaos/eliza#1706 (docs: update Twitter plugin README)"
}