{
  "version": "1.0",
  "type": "contributor",
  "interval": "day",
  "date": "2025-07-29",
  "generatedAt": "2026-01-20T23:15:08.905Z",
  "sourceLastUpdated": "2026-01-20T23:15:08.905Z",
  "contentFormat": "markdown",
  "contentHash": "c48cf240785bf29fd835492d5fc51803f900b09e7084288cd8ad3e227037eb57",
  "entity": {
    "username": "hesreallyhim"
  },
  "content": "hesreallyhim: Focused on community engagement by creating a new issue (elizaos/elizaos.github.io#149) to highlight a project feature."
}