{
  "version": "1.0",
  "type": "contributor",
  "interval": "lifetime",
  "date": "2026-01-11",
  "generatedAt": "2026-01-11T01:42:33.319Z",
  "sourceLastUpdated": "2026-01-11T01:42:33.319Z",
  "contentFormat": "markdown",
  "contentHash": "b350cc1711a286182b8065dbc27c7fde27e3827ea16ad6e251b851dd657fe4c6",
  "entity": {
    "username": "emg110"
  },
  "content": "# emg110\n\n## Activity Ledger\n- **Pull Requests Authored:** 0 merged, 0 open/closed\n- **Pull Requests Reviewed:** 0 total (0 approvals, 0 change requests, 0 comments)\n- **Issues:** 1 opened, 1 closed\n- **Avg Time to Merge:** 0 hours\n\n## Contribution Domains\n- **Feature Proposals:** Submitted request for blockchain integration.\n  - Issues: elizaos/eliza#1866 (Algorand Blockchain Integration Plugin)"
}