{
  "type": "dailySummary",
  "title": "Daily Summary for 2024-12-27",
  "categories": [
    {
      "title": "Crypto Market Price Update",
      "content": [
        {
          "text": "The latest cryptocurrency prices show fluctuations across various assets. Wrapped Bitcoin (WBTC) saw a decrease from $95,536.30 to $94,101.94. Wrapped Ethereum (WETH) experienced a slight dip from $3,330.43 to $3,327.40. Solana (SOL) also declined from $188.22 to $183.91. Meanwhile, ai16z token showed an increase from $0.81 to $0.93.",
          "sources": [
            "WBTC: $95,536.30 → $94,101.94",
            "WETH: $3,330.43 → $3,327.40",
            "SOL: $188.22 → $183.91",
            "ai16z: $0.81 → $0.93"
          ],
          "images": [],
          "videos": []
        }
      ],
      "topic": "crypto market"
    },
    {
      "title": "Recent Plugin Additions and Enhancements in ElizaOS",
      "content": [
        {
          "text": "A README file has been added for the TON plugin, providing documentation for its usage and integration.",
          "sources": [
            "https://github.com/elizaOS/eliza/pull/1496"
          ],
          "images": [
            "https://opengraph.githubassets.com/1/elizaOS/eliza/pull/1496"
          ],
          "videos": []
        },
        {
          "text": "A README file has been added for the WebSearch plugin, detailing its functionality and setup.",
          "sources": [
            "https://github.com/elizaOS/eliza/pull/1494"
          ],
          "images": [
            "https://opengraph.githubassets.com/1/elizaOS/eliza/pull/1494"
          ],
          "videos": []
        },
        {
          "text": "The FerePro plugin has been integrated, introducing structured WebSocket response handling via a new `ChatResponse` interface. It enhances WebSocket communication with validation, logging, and error handling.",
          "sources": [
            "https://github.com/elizaOS/eliza/pull/1502"
          ],
          "images": [
            "https://opengraph.githubassets.com/1/elizaOS/eliza/pull/1502"
          ],
          "videos": []
        },
        {
          "text": "A new Hyperliquid plugin has been added to the Eliza framework, enabling real-time WebSocket integration, market data access, and trading operations for the Hyperliquid perpetual DEX. It includes wallet-based authentication, message signing, and extensive test coverage.",
          "sources": [
            "https://github.com/elizaOS/eliza/pull/1497"
          ],
          "images": [
            "https://opengraph.githubassets.com/1/elizaOS/eliza/pull/1497"
          ],
          "videos": []
        },
        {
          "text": "The Vly Money plugin has been introduced, allowing users to convert Twitter usernames into Vly Money wallet addresses for seamless crypto transactions.",
          "sources": [
            "https://github.com/elizaOS/eliza/pull/1488"
          ],
          "images": [
            "https://opengraph.githubassets.com/1/elizaOS/eliza/pull/1488"
          ],
          "videos": []
        },
        {
          "text": "Support for cross-chain swaps through Squid Router has been added, enabling native and ERC20 token swaps across EVM-compatible chains. Future updates may extend support to Solana and Cosmos ecosystems.",
          "sources": [
            "https://github.com/elizaOS/eliza/pull/1482"
          ],
          "images": [
            "https://opengraph.githubassets.com/1/elizaOS/eliza/pull/1482"
          ],
          "videos": []
        }
      ],
      "topic": "plugin"
    },
    {
      "title": "Recent Updates and Proposals in ElizaOS Repository",
      "content": [
        {
          "text": "A new CODE_OF_CONDUCT.md file has been added to the repository to establish guidelines for open-source contributors. This document aims to ensure a welcoming and inclusive environment for all participants. The change is categorized as a document update with low risk, and no additional documentation changes are required.",
          "sources": [
            "https://github.com/elizaOS/eliza/pull/1487"
          ],
          "images": [
            "https://opengraph.githubassets.com/1/elizaOS/eliza/pull/1487"
          ],
          "videos": []
        },
        {
          "text": "A proposal has been made to set up linting, Prettier, and Husky in the repository. The current lint setup is outdated, leading to inconsistent code formatting. The proposal suggests implementing Husky for commit linting, updating GitHub Actions for CI linting, and enforcing linting rules in the community guidelines. Developer feedback is requested before proceeding.",
          "sources": [
            "https://github.com/elizaOS/eliza/issues/1486"
          ],
          "images": [
            "https://opengraph.githubassets.com/1/elizaOS/eliza/issues/1486"
          ],
          "videos": []
        },
        {
          "text": "A minor syntax issue in the ModelClass enum was fixed by adding a missing comma after the EMBEDDING value. This correction prevents potential compilation errors and ensures proper functionality.",
          "sources": [
            "https://github.com/elizaOS/eliza/pull/1493"
          ],
          "images": [
            "https://opengraph.githubassets.com/1/elizaOS/eliza/pull/1493"
          ],
          "videos": []
        },
        {
          "text": "An improvement was made to standardize import statements from ElizaOS by removing the 'type' keyword. This change enhances consistency across different plugin modules. The update is categorized as an improvement with low risk and does not require documentation changes.",
          "sources": [
            "https://github.com/elizaOS/eliza/pull/1492"
          ],
          "images": [
            "https://opengraph.githubassets.com/1/elizaOS/eliza/pull/1492"
          ],
          "videos": []
        }
      ],
      "topic": "code"
    },
    {
      "title": "Chat Transcript Analysis and Chat Formatting Improvement",
      "content": [
        {
          "text": "The provided chat transcript primarily consists of repeated messages from 'Captain Hook' and a single unique message from 'yikesawjeez' asking about adding a bot to their server. However, there is no substantial technical discussion, problem-solving, or meaningful interactions in the transcript, making it impossible to generate a structured analysis.",
          "sources": [
            "https://discord.com/channels/1253563208833433701/1326603270893867064"
          ],
          "images": [],
          "videos": []
        },
        {
          "text": "A pull request was made to improve chat formatting by properly handling line breaks and adjusting text alignment. The change is considered low-risk and is a simple cosmetic improvement to the chat client. Before and after images demonstrate the improved formatting.",
          "sources": [
            "https://github.com/elizaOS/eliza/pull/1483"
          ],
          "images": [
            "https://github.com/user-attachments/assets/08e6d0e2-c7e3-4c11-a08e-0fbb24f91fdd",
            "https://github.com/user-attachments/assets/fdd87d5d-467a-42d6-8e6e-eb3b256b7e93"
          ],
          "videos": []
        }
      ],
      "topic": "chat"
    },
    {
      "title": "TypeScript Fixes and Improvements in ElizaOS",
      "content": [
        {
          "text": "Two recent updates to the ElizaOS project address TypeScript-related issues, improving type safety and build performance.",
          "sources": [],
          "images": [],
          "videos": []
        },
        {
          "text": "The first update enhances TypeScript client type identification by introducing a `determineClientType` helper function. This resolves a TypeScript error where the `name` property was incorrectly assumed to exist on the `Client` type. The update also includes comprehensive test coverage to ensure reliability. These changes are internal and do not affect the public API.",
          "sources": [
            "https://github.com/elizaOS/eliza/pull/1490"
          ],
          "images": [
            "https://opengraph.githubassets.com/1/elizaOS/eliza/pull/1490"
          ],
          "videos": []
        },
        {
          "text": "The second update fixes TypeScript configuration errors encountered during the build process. It adds the required `incremental` option for `tsBuildInfoFile` usage, improving build performance by enabling proper incremental compilation. Additionally, it removes the invalid `noUncheckedSideEffectImports` compiler option, resolving a configuration error. These changes only affect development and build-time performance, with no impact on runtime behavior.",
          "sources": [
            "https://github.com/elizaOS/eliza/pull/1485"
          ],
          "images": [
            "https://opengraph.githubassets.com/1/elizaOS/eliza/pull/1485"
          ],
          "videos": []
        }
      ],
      "topic": "typescript"
    },
    {
      "title": "Documentation Update: Fixed Syntax Issue in ModelClass Fine-Tuning",
      "content": [
        {
          "text": "A small syntax issue in the 'ModelClass Update fine-tuning.md' documentation was fixed. This update ensures better readability and accuracy in the documentation.",
          "sources": [
            "https://github.com/elizaOS/eliza/commit/ed1e9f3d0f20020509e231bed81bda7f229a0b98",
            "https://github.com/elizaOS/eliza/commit/a930c84d4a1b1dde91fa3edb1374ee82a51623e2"
          ],
          "images": [
            "https://opengraph.githubassets.com/1/elizaOS/eliza/commit/ed1e9f3d0f20020509e231bed81bda7f229a0b98",
            "https://opengraph.githubassets.com/1/elizaOS/eliza/commit/a930c84d4a1b1dde91fa3edb1374ee82a51623e2"
          ],
          "videos": []
        }
      ],
      "topic": "fine-tuning"
    },
    {
      "title": "Installation Issues with pnpm and node-llama-cpp",
      "content": [
        {
          "text": "Users are experiencing installation failures when setting up node-llama-cpp. The installation process gets stuck during the quick start guide, specifically at the postinstall script for node-llama-cpp. The issue occurs with node version 23.3.0 and commit version 77b5b7d8 v0.1.7-alpha.1. Additionally, there are multiple warnings about deprecated dependencies and unmet peer dependencies.",
          "sources": [
            "https://github.com/elizaOS/eliza/issues/1503"
          ],
          "images": [
            "https://opengraph.githubassets.com/1/elizaOS/eliza/issues/1503"
          ],
          "videos": []
        },
        {
          "text": "Another issue has been reported where pnpm does not work properly when used within a project directory under Volta. While pnpm functions normally outside the project, attempting to execute it within the project directory results in a Volta error stating that the executable could not be located. The issue occurs with pnpm version 9.12.3.",
          "sources": [
            "https://github.com/elizaOS/eliza/issues/1484"
          ],
          "images": [
            "https://opengraph.githubassets.com/1/elizaOS/eliza/issues/1484"
          ],
          "videos": []
        }
      ],
      "topic": "dependencies"
    },
    {
      "title": "ElizaOS Development Updates",
      "content": [
        {
          "text": "The ElizaOS project saw significant development activity, with 19 contributors merging 11 pull requests. The updates included package improvements, new features, and three bug fixes.",
          "sources": [
            "Development focused on package improvements (add readme for ton plugin), new features (add readme for ton plugin), 3 bug fixes. with 19 contributors merging 11 PRs. Major work included various improvements."
          ],
          "images": [],
          "videos": []
        },
        {
          "text": "A new CODE_OF_CONDUCT.md file was added to ensure a welcoming and inclusive environment for open-source contributors.",
          "sources": [
            "https://github.com/elizaOS/eliza/pull/1487"
          ],
          "images": [
            "https://opengraph.githubassets.com/1/elizaOS/eliza/pull/1487"
          ],
          "videos": []
        },
        {
          "text": "A proposal was made to update the linting setup, including setting up Husky and commit interceptors to enforce code style consistency.",
          "sources": [
            "https://github.com/elizaOS/eliza/issues/1486"
          ],
          "images": [
            "https://opengraph.githubassets.com/1/elizaOS/eliza/issues/1486"
          ],
          "videos": []
        },
        {
          "text": "Readme files were added for the TON and WebSearch plugins to improve documentation.",
          "sources": [
            "https://github.com/elizaOS/eliza/pull/1496",
            "https://github.com/elizaOS/eliza/pull/1494"
          ],
          "images": [
            "https://opengraph.githubassets.com/1/elizaOS/eliza/pull/1496",
            "https://opengraph.githubassets.com/1/elizaOS/eliza/pull/1494"
          ],
          "videos": []
        },
        {
          "text": "A fix was implemented to improve TypeScript client type identification, ensuring better type safety and debugging.",
          "sources": [
            "https://github.com/elizaOS/eliza/pull/1490"
          ],
          "images": [
            "https://opengraph.githubassets.com/1/elizaOS/eliza/pull/1490"
          ],
          "videos": []
        },
        {
          "text": "TypeScript configuration was improved by adding the required incremental option and removing an invalid compiler setting.",
          "sources": [
            "https://github.com/elizaOS/eliza/pull/1485"
          ],
          "images": [
            "https://opengraph.githubassets.com/1/elizaOS/eliza/pull/1485"
          ],
          "videos": []
        },
        {
          "text": "A minor fix was made to correct typos in the project documentation.",
          "sources": [
            "https://github.com/elizaOS/eliza/pull/1489"
          ],
          "images": [
            "https://opengraph.githubassets.com/1/elizaOS/eliza/pull/1489"
          ],
          "videos": []
        },
        {
          "text": "Chat formatting was improved to better handle line breaks and text alignment.",
          "sources": [
            "https://github.com/elizaOS/eliza/pull/1483"
          ],
          "images": [
            "https://opengraph.githubassets.com/1/elizaOS/eliza/pull/1483"
          ],
          "videos": []
        },
        {
          "text": "A syntax issue in the ModelClass enum was fixed to prevent potential compilation errors.",
          "sources": [
            "https://github.com/elizaOS/eliza/pull/1493"
          ],
          "images": [
            "https://opengraph.githubassets.com/1/elizaOS/eliza/pull/1493"
          ],
          "videos": []
        },
        {
          "text": "The Twitter client was improved with better dry run mode handling and enhanced configuration logging.",
          "sources": [
            "https://github.com/elizaOS/eliza/pull/1498"
          ],
          "images": [
            "https://opengraph.githubassets.com/1/elizaOS/eliza/pull/1498"
          ],
          "videos": []
        },
        {
          "text": "Import consistency was improved by removing unnecessary 'type' declarations when importing from ElizaOS.",
          "sources": [
            "https://github.com/elizaOS/eliza/pull/1492"
          ],
          "images": [
            "https://opengraph.githubassets.com/1/elizaOS/eliza/pull/1492"
          ],
          "videos": []
        },
        {
          "text": "Broken links in the Eliza-in-TEE documentation were fixed to ensure proper navigation.",
          "sources": [
            "https://github.com/elizaOS/eliza/pull/1500"
          ],
          "images": [
            "https://opengraph.githubassets.com/1/elizaOS/eliza/pull/1500"
          ],
          "videos": []
        },
        {
          "text": "The parseBooleanFromText function was extended to support additional boolean values like 'ENABLE' and 'DISABLE'.",
          "sources": [
            "https://github.com/elizaOS/eliza/pull/1501"
          ],
          "images": [
            "https://opengraph.githubassets.com/1/elizaOS/eliza/pull/1501"
          ],
          "videos": []
        },
        {
          "text": "A new plugin for FerePro was added, introducing structured WebSocket response handling.",
          "sources": [
            "https://github.com/elizaOS/eliza/pull/1502"
          ],
          "images": [
            "https://opengraph.githubassets.com/1/elizaOS/eliza/pull/1502"
          ],
          "videos": []
        },
        {
          "text": "A Hyperliquid plugin was added to the Eliza framework, supporting WebSocket-based trading operations.",
          "sources": [
            "https://github.com/elizaOS/eliza/pull/1497"
          ],
          "images": [
            "https://opengraph.githubassets.com/1/elizaOS/eliza/pull/1497"
          ],
          "videos": []
        },
        {
          "text": "A new plugin was introduced to support the Vly Money API, enabling social media-based crypto transactions.",
          "sources": [
            "https://github.com/elizaOS/eliza/pull/1488"
          ],
          "images": [
            "https://opengraph.githubassets.com/1/elizaOS/eliza/pull/1488"
          ],
          "videos": []
        },
        {
          "text": "Cross-chain swaps were added to ElizaOS through the Squid Router, initially supporting EVM-based transactions.",
          "sources": [
            "https://github.com/elizaOS/eliza/pull/1482"
          ],
          "images": [
            "https://opengraph.githubassets.com/1/elizaOS/eliza/pull/1482"
          ],
          "videos": []
        },
        {
          "text": "Users reported installation issues with node-llama-cpp and better-sqlite3 when using plugin-tee.",
          "sources": [
            "https://github.com/elizaOS/eliza/issues/1503",
            "https://github.com/elizaOS/eliza/issues/1499"
          ],
          "images": [
            "https://opengraph.githubassets.com/1/elizaOS/eliza/issues/1503",
            "https://opengraph.githubassets.com/1/elizaOS/eliza/issues/1499"
          ],
          "videos": []
        },
        {
          "text": "A bug was reported where pnpm does not work correctly when using Volta.",
          "sources": [
            "https://github.com/elizaOS/eliza/issues/1484"
          ],
          "images": [
            "https://opengraph.githubassets.com/1/elizaOS/eliza/issues/1484"
          ],
          "videos": []
        }
      ],
      "topic": "Misceleanous"
    }
  ],
  "date": 1735257600
}