{
  "version": "1.0",
  "period": "monthly",
  "startDate": "2026-05-01",
  "endDate": "2026-05-01",
  "generatedAt": "2026-05-01T23:34:04.939Z",
  "totalUsers": 3,
  "leaderboard": [
    {
      "rank": 1,
      "username": "lalalune",
      "avatarUrl": "https://avatars.githubusercontent.com/u/18633264?u=e2e906c3712c2506ebfa98df01c2cfdc50050b30&v=4",
      "characterClass": "Builder",
      "tier": "beginner",
      "score": 34.924967478670574,
      "prScore": 34.58496747867057,
      "issueScore": 0,
      "reviewScore": 0,
      "commentScore": 0.33999999999999997,
      "wallets": {
        "ethereum": "0x1b324Bfc7A0b93D621d8A85F3fF6375528bFae8D",
        "solana": "5rZBMzhX4NiEwSGiJidacmY7HfGWKT41sE1PnpXBSLvG"
      },
      "focusAreas": [
        {
          "tag": "typescript",
          "score": 4894.5,
          "percentage": 29.86108145373353,
          "rank": 2,
          "totalInArea": 709
        },
        {
          "tag": "core",
          "score": 2582.5,
          "percentage": 15.755693708094157,
          "rank": 1,
          "totalInArea": 316
        },
        {
          "tag": "docs",
          "score": 2287.5,
          "percentage": 13.955914562348648,
          "rank": 2,
          "totalInArea": 603
        }
      ],
      "achievements": [
        {
          "type": "level",
          "tier": "elite",
          "earnedAt": "2025-10-27T23:09:13.435Z"
        },
        {
          "type": "streak",
          "tier": "beginner",
          "earnedAt": "2025-10-27T23:09:13.462Z"
        },
        {
          "type": "pr_master",
          "tier": "legend",
          "earnedAt": "2026-04-12T23:23:19.484Z"
        },
        {
          "type": "bug_hunter",
          "tier": "beginner",
          "earnedAt": "2025-10-27T23:09:13.481Z"
        },
        {
          "type": "review_champion",
          "tier": "elite",
          "earnedAt": "2025-10-27T23:09:13.498Z"
        }
      ],
      "profile": {
        "contributorType": "author",
        "prMergeRate": 100,
        "reviewActivity": "low"
      },
      "scoreBreakdown": {
        "total": 34.924967478670574,
        "distribution": {
          "prs": {
            "score": 34.58496747867057,
            "percentage": 99.02648441918336,
            "label": "Builder"
          },
          "issues": {
            "score": 0,
            "percentage": 0,
            "label": "Hunter"
          },
          "reviews": {
            "score": 0,
            "percentage": 0,
            "label": "Reviews"
          },
          "comments": {
            "score": 0.33999999999999997,
            "percentage": 0.9735155808166328,
            "label": "Engagement"
          }
        },
        "tier": "beginner",
        "percentile": 66.66666666666666,
        "characterClass": "Builder"
      },
      "links": {
        "profile": "https://elizaOS.github.io/profile/lalalune",
        "profileApi": "https://elizaOS.github.io/api/contributors/lalalune/profile.json",
        "summary": "https://elizaOS.github.io/api/summaries/contributors/lalalune/day/latest.json",
        "github": "https://github.com/lalalune"
      }
    },
    {
      "rank": 2,
      "username": "Sw4pIO",
      "avatarUrl": "https://avatars.githubusercontent.com/u/250003491?u=b9bad2342b9ccdb72ee4d4502d5534b6256e9d5c&v=4",
      "characterClass": "Hunter",
      "tier": "beginner",
      "score": 4,
      "prScore": 0,
      "issueScore": 4,
      "reviewScore": 0,
      "commentScore": 0,
      "wallets": {},
      "profile": {
        "contributorType": "author",
        "prMergeRate": 0,
        "reviewActivity": "low"
      },
      "scoreBreakdown": {
        "total": 4,
        "distribution": {
          "prs": {
            "score": 0,
            "percentage": 0,
            "label": "Builder"
          },
          "issues": {
            "score": 4,
            "percentage": 100,
            "label": "Hunter"
          },
          "reviews": {
            "score": 0,
            "percentage": 0,
            "label": "Reviews"
          },
          "comments": {
            "score": 0,
            "percentage": 0,
            "label": "Engagement"
          }
        },
        "tier": "beginner",
        "percentile": 33.33333333333333,
        "characterClass": "Hunter"
      },
      "links": {
        "profile": "https://elizaOS.github.io/profile/Sw4pIO",
        "profileApi": "https://elizaOS.github.io/api/contributors/Sw4pIO/profile.json",
        "summary": "https://elizaOS.github.io/api/summaries/contributors/Sw4pIO/day/latest.json",
        "github": "https://github.com/Sw4pIO"
      }
    },
    {
      "rank": 3,
      "username": "chopmob-cloud",
      "avatarUrl": "https://avatars.githubusercontent.com/u/250041792?u=295fb2375e2007927789532dae29a2c2bd3c5f80&v=4",
      "characterClass": "Contributor",
      "tier": "beginner",
      "score": 0.2,
      "prScore": 0,
      "issueScore": 0,
      "reviewScore": 0,
      "commentScore": 0.2,
      "wallets": {},
      "profile": {
        "contributorType": "author",
        "prMergeRate": 0,
        "reviewActivity": "low"
      },
      "scoreBreakdown": {
        "total": 0.2,
        "distribution": {
          "prs": {
            "score": 0,
            "percentage": 0,
            "label": "Builder"
          },
          "issues": {
            "score": 0,
            "percentage": 0,
            "label": "Hunter"
          },
          "reviews": {
            "score": 0,
            "percentage": 0,
            "label": "Reviews"
          },
          "comments": {
            "score": 0.2,
            "percentage": 100,
            "label": "Engagement"
          }
        },
        "tier": "beginner",
        "percentile": 0,
        "characterClass": "Contributor"
      },
      "links": {
        "profile": "https://elizaOS.github.io/profile/chopmob-cloud",
        "profileApi": "https://elizaOS.github.io/api/contributors/chopmob-cloud/profile.json",
        "summary": "https://elizaOS.github.io/api/summaries/contributors/chopmob-cloud/day/latest.json",
        "github": "https://github.com/chopmob-cloud"
      }
    }
  ]
}