{
  "version": "1.0",
  "period": "monthly",
  "startDate": "2026-05-01",
  "endDate": "2026-05-13",
  "generatedAt": "2026-05-13T23:41:21.059Z",
  "totalUsers": 20,
  "leaderboard": [
    {
      "rank": 1,
      "username": "2-A-M",
      "avatarUrl": "https://avatars.githubusercontent.com/u/96268540?u=b7d92c0e2a91af580d09eeae862eef576955ab8a&v=4",
      "characterClass": "Builder",
      "tier": "veteran",
      "score": 608.1063405616475,
      "prScore": 607.6683405616475,
      "issueScore": 0,
      "reviewScore": 0,
      "commentScore": 0.43799999999999994,
      "wallets": {},
      "focusAreas": [
        {
          "tag": "typescript",
          "score": 321,
          "percentage": 38.81030105186799,
          "rank": 20,
          "totalInArea": 711
        },
        {
          "tag": "core",
          "score": 167.5,
          "percentage": 20.251481078466938,
          "rank": 16,
          "totalInArea": 316
        },
        {
          "tag": "ui",
          "score": 115.19999999999987,
          "percentage": 13.928182807399336,
          "rank": 12,
          "totalInArea": 77
        }
      ],
      "achievements": [
        {
          "type": "pr_master",
          "tier": "elite",
          "earnedAt": "2026-05-03T23:29:54.629Z"
        },
        {
          "type": "level",
          "tier": "beginner",
          "earnedAt": "2026-04-28T23:29:54.294Z"
        }
      ],
      "profile": {
        "contributorType": "author",
        "prMergeRate": 75,
        "reviewActivity": "low"
      },
      "scoreBreakdown": {
        "total": 608.1063405616475,
        "distribution": {
          "prs": {
            "score": 607.6683405616475,
            "percentage": 99.92797312397772,
            "label": "Builder"
          },
          "issues": {
            "score": 0,
            "percentage": 0,
            "label": "Hunter"
          },
          "reviews": {
            "score": 0,
            "percentage": 0,
            "label": "Reviews"
          },
          "comments": {
            "score": 0.43799999999999994,
            "percentage": 0.0720268760222863,
            "label": "Engagement"
          }
        },
        "tier": "veteran",
        "percentile": 95,
        "characterClass": "Builder"
      },
      "links": {
        "profile": "https://elizaOS.github.io/profile/2-A-M",
        "profileApi": "https://elizaOS.github.io/api/contributors/2-A-M/profile.json",
        "summary": "https://elizaOS.github.io/api/summaries/contributors/2-A-M/day/latest.json",
        "github": "https://github.com/2-A-M"
      }
    },
    {
      "rank": 2,
      "username": "0xSolace",
      "avatarUrl": "https://avatars.githubusercontent.com/u/257989456?u=e0d4e0c6385403319241eb46ba647b49083d4a05&v=4",
      "characterClass": "Builder",
      "tier": "active",
      "score": 365.43402383270654,
      "prScore": 364.79602383270657,
      "issueScore": 0,
      "reviewScore": 0,
      "commentScore": 0.6379999999999999,
      "wallets": {},
      "focusAreas": [
        {
          "tag": "typescript",
          "score": 543,
          "percentage": 37.494821157298716,
          "rank": 13,
          "totalInArea": 711
        },
        {
          "tag": "react",
          "score": 156.80000000000032,
          "percentage": 10.827233807485177,
          "rank": 7,
          "totalInArea": 83
        },
        {
          "tag": "nextjs",
          "score": 156.7999999999997,
          "percentage": 10.827233807485134,
          "rank": 2,
          "totalInArea": 52
        }
      ],
      "achievements": [
        {
          "type": "level",
          "tier": "beginner",
          "earnedAt": "2026-04-21T23:23:22.720Z"
        },
        {
          "type": "pr_master",
          "tier": "beginner",
          "earnedAt": "2026-04-21T23:23:22.744Z"
        }
      ],
      "profile": {
        "contributorType": "author",
        "prMergeRate": 40,
        "reviewActivity": "low"
      },
      "scoreBreakdown": {
        "total": 365.43402383270654,
        "distribution": {
          "prs": {
            "score": 364.79602383270657,
            "percentage": 99.82541308187218,
            "label": "Builder"
          },
          "issues": {
            "score": 0,
            "percentage": 0,
            "label": "Hunter"
          },
          "reviews": {
            "score": 0,
            "percentage": 0,
            "label": "Reviews"
          },
          "comments": {
            "score": 0.6379999999999999,
            "percentage": 0.17458691812781846,
            "label": "Engagement"
          }
        },
        "tier": "active",
        "percentile": 90,
        "characterClass": "Builder"
      },
      "links": {
        "profile": "https://elizaOS.github.io/profile/0xSolace",
        "profileApi": "https://elizaOS.github.io/api/contributors/0xSolace/profile.json",
        "summary": "https://elizaOS.github.io/api/summaries/contributors/0xSolace/day/latest.json",
        "github": "https://github.com/0xSolace"
      }
    },
    {
      "rank": 3,
      "username": "standujar",
      "avatarUrl": "https://avatars.githubusercontent.com/u/16385918?u=718bdcd1585be8447bdfffb8c11ce249baa7532d&v=4",
      "characterClass": "Builder",
      "tier": "active",
      "score": 287.9106593561312,
      "prScore": 281.71065935613126,
      "issueScore": 0,
      "reviewScore": 6,
      "commentScore": 0.2,
      "wallets": {
        "ethereum": "0xf1d1CC42C3Cc1eE1A42D9eCbBa55E1C8cb4E1F04",
        "solana": "F6z7JdDQH6Yo7bopZegyKqzPnti4QfrVut6oacGsR2a3"
      },
      "focusAreas": [
        {
          "tag": "typescript",
          "score": 2641.5,
          "percentage": 39.618736220059084,
          "rank": 4,
          "totalInArea": 711
        },
        {
          "tag": "core",
          "score": 920,
          "percentage": 13.798689124533164,
          "rank": 6,
          "totalInArea": 316
        },
        {
          "tag": "tests",
          "score": 848,
          "percentage": 12.718791714787091,
          "rank": 3,
          "totalInArea": 193
        }
      ],
      "achievements": [
        {
          "type": "level",
          "tier": "elite",
          "earnedAt": "2025-12-03T23:10:09.371Z"
        },
        {
          "type": "streak",
          "tier": "beginner",
          "earnedAt": "2025-10-27T23:09:22.180Z"
        },
        {
          "type": "pr_master",
          "tier": "legend",
          "earnedAt": "2026-02-06T23:14:21.153Z"
        },
        {
          "type": "bug_hunter",
          "tier": "beginner",
          "earnedAt": "2025-10-27T23:09:22.226Z"
        },
        {
          "type": "review_champion",
          "tier": "elite",
          "earnedAt": "2025-12-18T23:11:26.879Z"
        }
      ],
      "profile": {
        "contributorType": "author",
        "prMergeRate": 71.4,
        "reviewActivity": "low"
      },
      "scoreBreakdown": {
        "total": 287.9106593561312,
        "distribution": {
          "prs": {
            "score": 281.71065935613126,
            "percentage": 97.84655420057553,
            "label": "Builder"
          },
          "issues": {
            "score": 0,
            "percentage": 0,
            "label": "Hunter"
          },
          "reviews": {
            "score": 6,
            "percentage": 2.083979805894681,
            "label": "Reviews"
          },
          "comments": {
            "score": 0.2,
            "percentage": 0.06946599352982272,
            "label": "Engagement"
          }
        },
        "tier": "active",
        "percentile": 85,
        "characterClass": "Builder"
      },
      "links": {
        "profile": "https://elizaOS.github.io/profile/standujar",
        "profileApi": "https://elizaOS.github.io/api/contributors/standujar/profile.json",
        "summary": "https://elizaOS.github.io/api/summaries/contributors/standujar/day/latest.json",
        "github": "https://github.com/standujar"
      }
    },
    {
      "rank": 4,
      "username": "greptile-apps",
      "avatarUrl": "https://avatars.githubusercontent.com/in/867647?v=4",
      "characterClass": "Contributor",
      "tier": "active",
      "score": 283.9,
      "prScore": 0,
      "issueScore": 0,
      "reviewScore": 283.5,
      "commentScore": 0.4,
      "wallets": {},
      "achievements": [
        {
          "type": "review_champion",
          "tier": "legend",
          "earnedAt": "2026-04-14T23:27:16.299Z"
        },
        {
          "type": "streak",
          "tier": "beginner",
          "earnedAt": "2026-01-31T23:11:58.257Z"
        }
      ],
      "profile": {
        "contributorType": "reviewer",
        "prMergeRate": 0,
        "reviewActivity": "high"
      },
      "scoreBreakdown": {
        "total": 283.9,
        "distribution": {
          "prs": {
            "score": 0,
            "percentage": 0,
            "label": "Builder"
          },
          "issues": {
            "score": 0,
            "percentage": 0,
            "label": "Hunter"
          },
          "reviews": {
            "score": 283.5,
            "percentage": 99.85910531877423,
            "label": "Reviews"
          },
          "comments": {
            "score": 0.4,
            "percentage": 0.14089468122578375,
            "label": "Engagement"
          }
        },
        "tier": "active",
        "percentile": 80,
        "characterClass": "Contributor"
      },
      "links": {
        "profile": "https://elizaOS.github.io/profile/greptile-apps",
        "profileApi": "https://elizaOS.github.io/api/contributors/greptile-apps/profile.json",
        "summary": "https://elizaOS.github.io/api/summaries/contributors/greptile-apps/day/latest.json",
        "github": "https://github.com/greptile-apps"
      }
    },
    {
      "rank": 5,
      "username": "NubsCarson",
      "avatarUrl": "https://avatars.githubusercontent.com/u/192162056?u=d2be9082dbee60fcbad21d32bf6e662ab1af3674&v=4",
      "characterClass": "Builder",
      "tier": "active",
      "score": 278.1006299851673,
      "prScore": 276.1006299851673,
      "issueScore": 2,
      "reviewScore": 0,
      "commentScore": 0,
      "wallets": {},
      "focusAreas": [
        {
          "tag": "typescript",
          "score": 351,
          "percentage": 37.36427506919311,
          "rank": 19,
          "totalInArea": 711
        },
        {
          "tag": "api",
          "score": 118.39999999999984,
          "percentage": 12.603789652969965,
          "rank": 9,
          "totalInArea": 206
        },
        {
          "tag": "ui",
          "score": 104.39999999999989,
          "percentage": 11.11347668724717,
          "rank": 13,
          "totalInArea": 77
        }
      ],
      "achievements": [
        {
          "type": "pr_master",
          "tier": "beginner",
          "earnedAt": "2026-04-25T23:23:38.743Z"
        },
        {
          "type": "level",
          "tier": "beginner",
          "earnedAt": "2026-04-27T23:29:26.792Z"
        }
      ],
      "profile": {
        "contributorType": "author",
        "prMergeRate": 100,
        "reviewActivity": "low"
      },
      "scoreBreakdown": {
        "total": 278.1006299851673,
        "distribution": {
          "prs": {
            "score": 276.1006299851673,
            "percentage": 99.28083586142661,
            "label": "Builder"
          },
          "issues": {
            "score": 2,
            "percentage": 0.7191641385733902,
            "label": "Hunter"
          },
          "reviews": {
            "score": 0,
            "percentage": 0,
            "label": "Reviews"
          },
          "comments": {
            "score": 0,
            "percentage": 0,
            "label": "Engagement"
          }
        },
        "tier": "active",
        "percentile": 75,
        "characterClass": "Builder"
      },
      "links": {
        "profile": "https://elizaOS.github.io/profile/NubsCarson",
        "profileApi": "https://elizaOS.github.io/api/contributors/NubsCarson/profile.json",
        "summary": "https://elizaOS.github.io/api/summaries/contributors/NubsCarson/day/latest.json",
        "github": "https://github.com/NubsCarson"
      }
    },
    {
      "rank": 6,
      "username": "ezumba",
      "avatarUrl": "https://avatars.githubusercontent.com/u/10479651?v=4",
      "characterClass": "Scribe",
      "tier": "active",
      "score": 202.55430756779697,
      "prScore": 188.61630756779698,
      "issueScore": 0,
      "reviewScore": 13.5,
      "commentScore": 0.43799999999999994,
      "wallets": {},
      "focusAreas": [
        {
          "tag": "docs",
          "score": 19.5,
          "percentage": 41.935483870967744,
          "rank": 94,
          "totalInArea": 605
        },
        {
          "tag": "typescript",
          "score": 18,
          "percentage": 38.70967741935484,
          "rank": 265,
          "totalInArea": 711
        },
        {
          "tag": "architect",
          "score": 5,
          "percentage": 10.75268817204301,
          "rank": 129,
          "totalInArea": 372
        }
      ],
      "profile": {
        "contributorType": "author",
        "prMergeRate": 0,
        "reviewActivity": "low"
      },
      "scoreBreakdown": {
        "total": 202.55430756779697,
        "distribution": {
          "prs": {
            "score": 188.61630756779698,
            "percentage": 93.11888245312443,
            "label": "Builder"
          },
          "issues": {
            "score": 0,
            "percentage": 0,
            "label": "Hunter"
          },
          "reviews": {
            "score": 13.5,
            "percentage": 6.664879242561363,
            "label": "Reviews"
          },
          "comments": {
            "score": 0.43799999999999994,
            "percentage": 0.2162383043142131,
            "label": "Engagement"
          }
        },
        "tier": "active",
        "percentile": 70,
        "characterClass": "Scribe"
      },
      "links": {
        "profile": "https://elizaOS.github.io/profile/ezumba",
        "profileApi": "https://elizaOS.github.io/api/contributors/ezumba/profile.json",
        "summary": "https://elizaOS.github.io/api/summaries/contributors/ezumba/day/latest.json",
        "github": "https://github.com/ezumba"
      }
    },
    {
      "rank": 7,
      "username": "lalalune",
      "avatarUrl": "https://avatars.githubusercontent.com/u/18633264?u=e2e906c3712c2506ebfa98df01c2cfdc50050b30&v=4",
      "characterClass": "Builder",
      "tier": "regular",
      "score": 149.69582141615683,
      "prScore": 148.47982141615682,
      "issueScore": 0,
      "reviewScore": 0,
      "commentScore": 1.2159999999999997,
      "wallets": {
        "ethereum": "0x1b324Bfc7A0b93D621d8A85F3fF6375528bFae8D",
        "solana": "5rZBMzhX4NiEwSGiJidacmY7HfGWKT41sE1PnpXBSLvG"
      },
      "focusAreas": [
        {
          "tag": "typescript",
          "score": 5005.5,
          "percentage": 30.037986305726815,
          "rank": 2,
          "totalInArea": 711
        },
        {
          "tag": "core",
          "score": 2582.5,
          "percentage": 15.497572597051143,
          "rank": 1,
          "totalInArea": 316
        },
        {
          "tag": "docs",
          "score": 2290.5,
          "percentage": 13.745281716765012,
          "rank": 2,
          "totalInArea": 605
        }
      ],
      "achievements": [
        {
          "type": "level",
          "tier": "legend",
          "earnedAt": "2026-05-02T23:27:30.440Z"
        },
        {
          "type": "streak",
          "tier": "beginner",
          "earnedAt": "2025-10-27T23:09:13.462Z"
        },
        {
          "type": "pr_master",
          "tier": "legend",
          "earnedAt": "2026-04-12T23:23:19.484Z"
        },
        {
          "type": "bug_hunter",
          "tier": "beginner",
          "earnedAt": "2025-10-27T23:09:13.481Z"
        },
        {
          "type": "review_champion",
          "tier": "elite",
          "earnedAt": "2025-10-27T23:09:13.498Z"
        }
      ],
      "profile": {
        "contributorType": "author",
        "prMergeRate": 75,
        "reviewActivity": "low"
      },
      "scoreBreakdown": {
        "total": 149.69582141615683,
        "distribution": {
          "prs": {
            "score": 148.47982141615682,
            "percentage": 99.18768607667444,
            "label": "Builder"
          },
          "issues": {
            "score": 0,
            "percentage": 0,
            "label": "Hunter"
          },
          "reviews": {
            "score": 0,
            "percentage": 0,
            "label": "Reviews"
          },
          "comments": {
            "score": 1.2159999999999997,
            "percentage": 0.8123139233255549,
            "label": "Engagement"
          }
        },
        "tier": "regular",
        "percentile": 65,
        "characterClass": "Builder"
      },
      "links": {
        "profile": "https://elizaOS.github.io/profile/lalalune",
        "profileApi": "https://elizaOS.github.io/api/contributors/lalalune/profile.json",
        "summary": "https://elizaOS.github.io/api/summaries/contributors/lalalune/day/latest.json",
        "github": "https://github.com/lalalune"
      }
    },
    {
      "rank": 8,
      "username": "Dexploarer",
      "avatarUrl": "https://avatars.githubusercontent.com/u/211557447?u=21a243d61cc1f87574328ae07fc64d7d7577b53d&v=4",
      "characterClass": "Builder",
      "tier": "beginner",
      "score": 31.94591014905531,
      "prScore": 31.94591014905531,
      "issueScore": 0,
      "reviewScore": 0,
      "commentScore": 0,
      "wallets": {
        "ethereum": "0x215bfEeBdbB48a3ca1b0362294fD4fa89F25Aa59",
        "solana": "2V7ZZ96oJX6DLQZHj83hsevJw2uLsrfMQZ5GUWRdRuj7"
      },
      "focusAreas": [
        {
          "tag": "typescript",
          "score": 667.5,
          "percentage": 31.555807686852923,
          "rank": 11,
          "totalInArea": 711
        },
        {
          "tag": "core",
          "score": 547.5,
          "percentage": 25.882853495958013,
          "rank": 9,
          "totalInArea": 316
        },
        {
          "tag": "ui",
          "score": 225.00000000000045,
          "percentage": 10.63678910792797,
          "rank": 5,
          "totalInArea": 77
        }
      ],
      "achievements": [
        {
          "type": "level",
          "tier": "beginner",
          "earnedAt": "2025-10-27T23:09:22.451Z"
        },
        {
          "type": "pr_master",
          "tier": "beginner",
          "earnedAt": "2026-04-25T23:23:37.694Z"
        }
      ],
      "profile": {
        "contributorType": "author",
        "prMergeRate": 100,
        "reviewActivity": "low"
      },
      "scoreBreakdown": {
        "total": 31.94591014905531,
        "distribution": {
          "prs": {
            "score": 31.94591014905531,
            "percentage": 100,
            "label": "Builder"
          },
          "issues": {
            "score": 0,
            "percentage": 0,
            "label": "Hunter"
          },
          "reviews": {
            "score": 0,
            "percentage": 0,
            "label": "Reviews"
          },
          "comments": {
            "score": 0,
            "percentage": 0,
            "label": "Engagement"
          }
        },
        "tier": "beginner",
        "percentile": 60,
        "characterClass": "Builder"
      },
      "links": {
        "profile": "https://elizaOS.github.io/profile/Dexploarer",
        "profileApi": "https://elizaOS.github.io/api/contributors/Dexploarer/profile.json",
        "summary": "https://elizaOS.github.io/api/summaries/contributors/Dexploarer/day/latest.json",
        "github": "https://github.com/Dexploarer"
      }
    },
    {
      "rank": 9,
      "username": "dutchiono",
      "avatarUrl": "https://avatars.githubusercontent.com/u/86275975?u=0d8badaa81aa47682651f87dc2d363837876de98&v=4",
      "characterClass": "Builder",
      "tier": "beginner",
      "score": 31.198947636399186,
      "prScore": 31.198947636399186,
      "issueScore": 0,
      "reviewScore": 0,
      "commentScore": 0,
      "wallets": {},
      "focusAreas": [
        {
          "tag": "typescript",
          "score": 150,
          "percentage": 46.845721424109925,
          "rank": 32,
          "totalInArea": 711
        },
        {
          "tag": "core",
          "score": 60,
          "percentage": 18.73828856964397,
          "rank": 40,
          "totalInArea": 316
        },
        {
          "tag": "api",
          "score": 24.000000000000004,
          "percentage": 7.495315427857589,
          "rank": 34,
          "totalInArea": 206
        }
      ],
      "achievements": [
        {
          "type": "pr_master",
          "tier": "beginner",
          "earnedAt": "2026-04-22T23:28:04.073Z"
        }
      ],
      "profile": {
        "contributorType": "author",
        "prMergeRate": 100,
        "reviewActivity": "low"
      },
      "scoreBreakdown": {
        "total": 31.198947636399186,
        "distribution": {
          "prs": {
            "score": 31.198947636399186,
            "percentage": 100,
            "label": "Builder"
          },
          "issues": {
            "score": 0,
            "percentage": 0,
            "label": "Hunter"
          },
          "reviews": {
            "score": 0,
            "percentage": 0,
            "label": "Reviews"
          },
          "comments": {
            "score": 0,
            "percentage": 0,
            "label": "Engagement"
          }
        },
        "tier": "beginner",
        "percentile": 55.00000000000001,
        "characterClass": "Builder"
      },
      "links": {
        "profile": "https://elizaOS.github.io/profile/dutchiono",
        "profileApi": "https://elizaOS.github.io/api/contributors/dutchiono/profile.json",
        "summary": "https://elizaOS.github.io/api/summaries/contributors/dutchiono/day/latest.json",
        "github": "https://github.com/dutchiono"
      }
    },
    {
      "rank": 10,
      "username": "Sw4pIO",
      "avatarUrl": "https://avatars.githubusercontent.com/u/250003491?u=b9bad2342b9ccdb72ee4d4502d5534b6256e9d5c&v=4",
      "characterClass": "Hunter",
      "tier": "beginner",
      "score": 24,
      "prScore": 0,
      "issueScore": 24,
      "reviewScore": 0,
      "commentScore": 0,
      "wallets": {},
      "achievements": [
        {
          "type": "bug_hunter",
          "tier": "beginner",
          "earnedAt": "2026-05-03T23:30:07.088Z"
        }
      ],
      "profile": {
        "contributorType": "author",
        "prMergeRate": 0,
        "reviewActivity": "low"
      },
      "scoreBreakdown": {
        "total": 24,
        "distribution": {
          "prs": {
            "score": 0,
            "percentage": 0,
            "label": "Builder"
          },
          "issues": {
            "score": 24,
            "percentage": 100,
            "label": "Hunter"
          },
          "reviews": {
            "score": 0,
            "percentage": 0,
            "label": "Reviews"
          },
          "comments": {
            "score": 0,
            "percentage": 0,
            "label": "Engagement"
          }
        },
        "tier": "beginner",
        "percentile": 50,
        "characterClass": "Hunter"
      },
      "links": {
        "profile": "https://elizaOS.github.io/profile/Sw4pIO",
        "profileApi": "https://elizaOS.github.io/api/contributors/Sw4pIO/profile.json",
        "summary": "https://elizaOS.github.io/api/summaries/contributors/Sw4pIO/day/latest.json",
        "github": "https://github.com/Sw4pIO"
      }
    },
    {
      "rank": 11,
      "username": "vyctorbrzezowski",
      "avatarUrl": "https://avatars.githubusercontent.com/u/51521767?u=9cd153e7883fb4e8486fe44817b3ae46a6a3df22&v=4",
      "characterClass": "Builder",
      "tier": "beginner",
      "score": 21.0695263639469,
      "prScore": 21.0695263639469,
      "issueScore": 0,
      "reviewScore": 0,
      "commentScore": 0,
      "wallets": {},
      "focusAreas": [
        {
          "tag": "typescript",
          "score": 4.5,
          "percentage": 42.056074766355145,
          "rank": 526,
          "totalInArea": 711
        },
        {
          "tag": "bug-fixer",
          "score": 2.2,
          "percentage": 20.560747663551403,
          "rank": 237,
          "totalInArea": 237
        },
        {
          "tag": "tests",
          "score": 2,
          "percentage": 18.691588785046733,
          "rank": 193,
          "totalInArea": 193
        }
      ],
      "profile": {
        "contributorType": "author",
        "prMergeRate": 0,
        "reviewActivity": "low"
      },
      "scoreBreakdown": {
        "total": 21.0695263639469,
        "distribution": {
          "prs": {
            "score": 21.0695263639469,
            "percentage": 100,
            "label": "Builder"
          },
          "issues": {
            "score": 0,
            "percentage": 0,
            "label": "Hunter"
          },
          "reviews": {
            "score": 0,
            "percentage": 0,
            "label": "Reviews"
          },
          "comments": {
            "score": 0,
            "percentage": 0,
            "label": "Engagement"
          }
        },
        "tier": "beginner",
        "percentile": 45,
        "characterClass": "Builder"
      },
      "links": {
        "profile": "https://elizaOS.github.io/profile/vyctorbrzezowski",
        "profileApi": "https://elizaOS.github.io/api/contributors/vyctorbrzezowski/profile.json",
        "summary": "https://elizaOS.github.io/api/summaries/contributors/vyctorbrzezowski/day/latest.json",
        "github": "https://github.com/vyctorbrzezowski"
      }
    },
    {
      "rank": 12,
      "username": "Aigen-Protocol",
      "avatarUrl": "https://avatars.githubusercontent.com/u/83247083?u=8c9172a589d1dc3ecb7359ec620a0170f68e84e2&v=4",
      "characterClass": "Scribe",
      "tier": "beginner",
      "score": 18.7693137373023,
      "prScore": 18.7693137373023,
      "issueScore": 0,
      "reviewScore": 0,
      "commentScore": 0,
      "wallets": {},
      "focusAreas": [
        {
          "tag": "docs",
          "score": 1.5,
          "percentage": 100,
          "rank": 605,
          "totalInArea": 605
        }
      ],
      "profile": {
        "contributorType": "author",
        "prMergeRate": 0,
        "reviewActivity": "low"
      },
      "scoreBreakdown": {
        "total": 18.7693137373023,
        "distribution": {
          "prs": {
            "score": 18.7693137373023,
            "percentage": 100,
            "label": "Builder"
          },
          "issues": {
            "score": 0,
            "percentage": 0,
            "label": "Hunter"
          },
          "reviews": {
            "score": 0,
            "percentage": 0,
            "label": "Reviews"
          },
          "comments": {
            "score": 0,
            "percentage": 0,
            "label": "Engagement"
          }
        },
        "tier": "beginner",
        "percentile": 40,
        "characterClass": "Scribe"
      },
      "links": {
        "profile": "https://elizaOS.github.io/profile/Aigen-Protocol",
        "profileApi": "https://elizaOS.github.io/api/contributors/Aigen-Protocol/profile.json",
        "summary": "https://elizaOS.github.io/api/summaries/contributors/Aigen-Protocol/day/latest.json",
        "github": "https://github.com/Aigen-Protocol"
      }
    },
    {
      "rank": 13,
      "username": "RemilioNubilio",
      "avatarUrl": "https://avatars.githubusercontent.com/u/275382225?u=b1501ee01bb54e5b31ca64895f2a07c69f554a37&v=4",
      "characterClass": "Builder",
      "tier": "beginner",
      "score": 16.693147180559947,
      "prScore": 14.693147180559945,
      "issueScore": 2,
      "reviewScore": 0,
      "commentScore": 0,
      "wallets": {},
      "focusAreas": [
        {
          "tag": "typescript",
          "score": 64.5,
          "percentage": 36.92043503148255,
          "rank": 73,
          "totalInArea": 711
        },
        {
          "tag": "docs",
          "score": 22.5,
          "percentage": 12.879221522610191,
          "rank": 84,
          "totalInArea": 605
        },
        {
          "tag": "core",
          "score": 22.5,
          "percentage": 12.879221522610191,
          "rank": 101,
          "totalInArea": 316
        }
      ],
      "achievements": [
        {
          "type": "pr_master",
          "tier": "beginner",
          "earnedAt": "2026-04-24T23:24:26.483Z"
        }
      ],
      "profile": {
        "contributorType": "author",
        "prMergeRate": 0,
        "reviewActivity": "low"
      },
      "scoreBreakdown": {
        "total": 16.693147180559947,
        "distribution": {
          "prs": {
            "score": 14.693147180559945,
            "percentage": 88.01903572545561,
            "label": "Builder"
          },
          "issues": {
            "score": 2,
            "percentage": 11.98096427454438,
            "label": "Hunter"
          },
          "reviews": {
            "score": 0,
            "percentage": 0,
            "label": "Reviews"
          },
          "comments": {
            "score": 0,
            "percentage": 0,
            "label": "Engagement"
          }
        },
        "tier": "beginner",
        "percentile": 35,
        "characterClass": "Builder"
      },
      "links": {
        "profile": "https://elizaOS.github.io/profile/RemilioNubilio",
        "profileApi": "https://elizaOS.github.io/api/contributors/RemilioNubilio/profile.json",
        "summary": "https://elizaOS.github.io/api/summaries/contributors/RemilioNubilio/day/latest.json",
        "github": "https://github.com/RemilioNubilio"
      }
    },
    {
      "rank": 14,
      "username": "github-code-quality",
      "avatarUrl": "https://avatars.githubusercontent.com/u/9919?v=4",
      "characterClass": "Contributor",
      "tier": "beginner",
      "score": 13.5,
      "prScore": 0,
      "issueScore": 0,
      "reviewScore": 13.5,
      "commentScore": 0,
      "wallets": {},
      "profile": {
        "contributorType": "reviewer",
        "prMergeRate": 0,
        "reviewActivity": "low"
      },
      "scoreBreakdown": {
        "total": 13.5,
        "distribution": {
          "prs": {
            "score": 0,
            "percentage": 0,
            "label": "Builder"
          },
          "issues": {
            "score": 0,
            "percentage": 0,
            "label": "Hunter"
          },
          "reviews": {
            "score": 13.5,
            "percentage": 100,
            "label": "Reviews"
          },
          "comments": {
            "score": 0,
            "percentage": 0,
            "label": "Engagement"
          }
        },
        "tier": "beginner",
        "percentile": 30,
        "characterClass": "Contributor"
      },
      "links": {
        "profile": "https://elizaOS.github.io/profile/github-code-quality",
        "profileApi": "https://elizaOS.github.io/api/contributors/github-code-quality/profile.json",
        "summary": "https://elizaOS.github.io/api/summaries/contributors/github-code-quality/day/latest.json",
        "github": "https://github.com/github-code-quality"
      }
    },
    {
      "rank": 15,
      "username": "aUsABuisnessman",
      "avatarUrl": "https://avatars.githubusercontent.com/u/104612281?u=d9592adc888957874f7fc163df901269fb5f44af&v=4",
      "characterClass": "Builder",
      "tier": "beginner",
      "score": 11.084573590279971,
      "prScore": 11.084573590279971,
      "issueScore": 0,
      "reviewScore": 0,
      "commentScore": 0,
      "wallets": {},
      "focusAreas": [
        {
          "tag": "nextjs",
          "score": 3.2,
          "percentage": 100,
          "rank": 40,
          "totalInArea": 52
        }
      ],
      "profile": {
        "contributorType": "author",
        "prMergeRate": 0,
        "reviewActivity": "low"
      },
      "scoreBreakdown": {
        "total": 11.084573590279971,
        "distribution": {
          "prs": {
            "score": 11.084573590279971,
            "percentage": 100,
            "label": "Builder"
          },
          "issues": {
            "score": 0,
            "percentage": 0,
            "label": "Hunter"
          },
          "reviews": {
            "score": 0,
            "percentage": 0,
            "label": "Reviews"
          },
          "comments": {
            "score": 0,
            "percentage": 0,
            "label": "Engagement"
          }
        },
        "tier": "beginner",
        "percentile": 25,
        "characterClass": "Builder"
      },
      "links": {
        "profile": "https://elizaOS.github.io/profile/aUsABuisnessman",
        "profileApi": "https://elizaOS.github.io/api/contributors/aUsABuisnessman/profile.json",
        "summary": "https://elizaOS.github.io/api/summaries/contributors/aUsABuisnessman/day/latest.json",
        "github": "https://github.com/aUsABuisnessman"
      }
    },
    {
      "rank": 16,
      "username": "Agnuxo1",
      "avatarUrl": "https://avatars.githubusercontent.com/u/166046035?u=4654f0706d2f6e9cf6894bd6717003d19f74645c&v=4",
      "characterClass": "Hunter",
      "tier": "beginner",
      "score": 4,
      "prScore": 0,
      "issueScore": 4,
      "reviewScore": 0,
      "commentScore": 0,
      "wallets": {},
      "profile": {
        "contributorType": "author",
        "prMergeRate": 0,
        "reviewActivity": "low"
      },
      "scoreBreakdown": {
        "total": 4,
        "distribution": {
          "prs": {
            "score": 0,
            "percentage": 0,
            "label": "Builder"
          },
          "issues": {
            "score": 4,
            "percentage": 100,
            "label": "Hunter"
          },
          "reviews": {
            "score": 0,
            "percentage": 0,
            "label": "Reviews"
          },
          "comments": {
            "score": 0,
            "percentage": 0,
            "label": "Engagement"
          }
        },
        "tier": "beginner",
        "percentile": 20,
        "characterClass": "Hunter"
      },
      "links": {
        "profile": "https://elizaOS.github.io/profile/Agnuxo1",
        "profileApi": "https://elizaOS.github.io/api/contributors/Agnuxo1/profile.json",
        "summary": "https://elizaOS.github.io/api/summaries/contributors/Agnuxo1/day/latest.json",
        "github": "https://github.com/Agnuxo1"
      }
    },
    {
      "rank": 17,
      "username": "andex23",
      "avatarUrl": "https://avatars.githubusercontent.com/u/49397867?u=760e6ec36b34f3511f24928686d87f912c3eb7ba&v=4",
      "characterClass": "Hunter",
      "tier": "beginner",
      "score": 2,
      "prScore": 0,
      "issueScore": 2,
      "reviewScore": 0,
      "commentScore": 0,
      "wallets": {},
      "focusAreas": [
        {
          "tag": "typescript",
          "score": 3,
          "percentage": 41.666666666666664,
          "rank": 614,
          "totalInArea": 711
        },
        {
          "tag": "bug-fixer",
          "score": 2.2,
          "percentage": 30.555555555555557,
          "rank": 236,
          "totalInArea": 237
        },
        {
          "tag": "maintainer",
          "score": 2,
          "percentage": 27.77777777777778,
          "rank": 301,
          "totalInArea": 302
        }
      ],
      "profile": {
        "contributorType": "author",
        "prMergeRate": 0,
        "reviewActivity": "low"
      },
      "scoreBreakdown": {
        "total": 2,
        "distribution": {
          "prs": {
            "score": 0,
            "percentage": 0,
            "label": "Builder"
          },
          "issues": {
            "score": 2,
            "percentage": 100,
            "label": "Hunter"
          },
          "reviews": {
            "score": 0,
            "percentage": 0,
            "label": "Reviews"
          },
          "comments": {
            "score": 0,
            "percentage": 0,
            "label": "Engagement"
          }
        },
        "tier": "beginner",
        "percentile": 15,
        "characterClass": "Hunter"
      },
      "links": {
        "profile": "https://elizaOS.github.io/profile/andex23",
        "profileApi": "https://elizaOS.github.io/api/contributors/andex23/profile.json",
        "summary": "https://elizaOS.github.io/api/summaries/contributors/andex23/day/latest.json",
        "github": "https://github.com/andex23"
      }
    },
    {
      "rank": 18,
      "username": "jasonxkensei",
      "avatarUrl": "https://avatars.githubusercontent.com/u/260305565?u=b17387a9077530191e297ff256d49d9a14c47194&v=4",
      "characterClass": "Contributor",
      "tier": "beginner",
      "score": 0.2,
      "prScore": 0,
      "issueScore": 0,
      "reviewScore": 0,
      "commentScore": 0.2,
      "wallets": {},
      "focusAreas": [
        {
          "tag": "architect",
          "score": 2.5,
          "percentage": 55.55555555555556,
          "rank": 358,
          "totalInArea": 372
        },
        {
          "tag": "feature-dev",
          "score": 2,
          "percentage": 44.44444444444444,
          "rank": 354,
          "totalInArea": 368
        }
      ],
      "profile": {
        "contributorType": "author",
        "prMergeRate": 0,
        "reviewActivity": "low"
      },
      "scoreBreakdown": {
        "total": 0.2,
        "distribution": {
          "prs": {
            "score": 0,
            "percentage": 0,
            "label": "Builder"
          },
          "issues": {
            "score": 0,
            "percentage": 0,
            "label": "Hunter"
          },
          "reviews": {
            "score": 0,
            "percentage": 0,
            "label": "Reviews"
          },
          "comments": {
            "score": 0.2,
            "percentage": 100,
            "label": "Engagement"
          }
        },
        "tier": "beginner",
        "percentile": 10,
        "characterClass": "Contributor"
      },
      "links": {
        "profile": "https://elizaOS.github.io/profile/jasonxkensei",
        "profileApi": "https://elizaOS.github.io/api/contributors/jasonxkensei/profile.json",
        "summary": "https://elizaOS.github.io/api/summaries/contributors/jasonxkensei/day/latest.json",
        "github": "https://github.com/jasonxkensei"
      }
    },
    {
      "rank": 19,
      "username": "chopmob-cloud",
      "avatarUrl": "https://avatars.githubusercontent.com/u/250041792?u=295fb2375e2007927789532dae29a2c2bd3c5f80&v=4",
      "characterClass": "Contributor",
      "tier": "beginner",
      "score": 0.2,
      "prScore": 0,
      "issueScore": 0,
      "reviewScore": 0,
      "commentScore": 0.2,
      "wallets": {},
      "profile": {
        "contributorType": "author",
        "prMergeRate": 0,
        "reviewActivity": "low"
      },
      "scoreBreakdown": {
        "total": 0.2,
        "distribution": {
          "prs": {
            "score": 0,
            "percentage": 0,
            "label": "Builder"
          },
          "issues": {
            "score": 0,
            "percentage": 0,
            "label": "Hunter"
          },
          "reviews": {
            "score": 0,
            "percentage": 0,
            "label": "Reviews"
          },
          "comments": {
            "score": 0.2,
            "percentage": 100,
            "label": "Engagement"
          }
        },
        "tier": "beginner",
        "percentile": 5,
        "characterClass": "Contributor"
      },
      "links": {
        "profile": "https://elizaOS.github.io/profile/chopmob-cloud",
        "profileApi": "https://elizaOS.github.io/api/contributors/chopmob-cloud/profile.json",
        "summary": "https://elizaOS.github.io/api/summaries/contributors/chopmob-cloud/day/latest.json",
        "github": "https://github.com/chopmob-cloud"
      }
    },
    {
      "rank": 20,
      "username": "bartonguestier1725-collab",
      "avatarUrl": "https://avatars.githubusercontent.com/u/249058300?v=4",
      "characterClass": "Contributor",
      "tier": "beginner",
      "score": 0.2,
      "prScore": 0,
      "issueScore": 0,
      "reviewScore": 0,
      "commentScore": 0.2,
      "wallets": {},
      "focusAreas": [
        {
          "tag": "architect",
          "score": 2.5,
          "percentage": 55.55555555555556,
          "rank": 372,
          "totalInArea": 372
        },
        {
          "tag": "feature-dev",
          "score": 2,
          "percentage": 44.44444444444444,
          "rank": 368,
          "totalInArea": 368
        }
      ],
      "profile": {
        "contributorType": "author",
        "prMergeRate": 0,
        "reviewActivity": "low"
      },
      "scoreBreakdown": {
        "total": 0.2,
        "distribution": {
          "prs": {
            "score": 0,
            "percentage": 0,
            "label": "Builder"
          },
          "issues": {
            "score": 0,
            "percentage": 0,
            "label": "Hunter"
          },
          "reviews": {
            "score": 0,
            "percentage": 0,
            "label": "Reviews"
          },
          "comments": {
            "score": 0.2,
            "percentage": 100,
            "label": "Engagement"
          }
        },
        "tier": "beginner",
        "percentile": 0,
        "characterClass": "Contributor"
      },
      "links": {
        "profile": "https://elizaOS.github.io/profile/bartonguestier1725-collab",
        "profileApi": "https://elizaOS.github.io/api/contributors/bartonguestier1725-collab/profile.json",
        "summary": "https://elizaOS.github.io/api/summaries/contributors/bartonguestier1725-collab/day/latest.json",
        "github": "https://github.com/bartonguestier1725-collab"
      }
    }
  ]
}