{
  "server": "Hyperfy",
  "title": "Hyperfy Discord - 2025-10-20",
  "date": 1760918400,
  "stats": {
    "totalMessages": 1,
    "totalUsers": 1
  },
  "categories": [
    {
      "channelId": "1326789867312775290",
      "channelName": "🪙│hyper",
      "summary": "The chat segment is extremely brief, containing only a single message from user MetaDJ commenting on price volatility over a two-day period. There are no technical discussions, decisions, problem-solving activities, solutions, or implementations present in this limited exchange.",
      "messageCount": 1,
      "userCount": 1
    }
  ]
}