{
  "version": "1.0",
  "username": "lalalune",
  "generatedAt": "2026-05-29T23:46:27.000Z",
  "characterSheet": {
    "tier": "legend",
    "characterClass": "Builder",
    "percentile": 99.68612680477086,
    "rank": {
      "monthly": 3,
      "weekly": 7,
      "lifetime": 5
    },
    "scoreBreakdown": {
      "total": 9227.926881598349,
      "distribution": {
        "prs": {
          "score": 8468.75288159835,
          "percentage": 91.77308175779018,
          "label": "Builder"
        },
        "issues": {
          "score": 302.8,
          "percentage": 3.281343728501159,
          "label": "Hunter"
        },
        "reviews": {
          "score": 426.5,
          "percentage": 4.621839828948958,
          "label": "Reviews"
        },
        "comments": {
          "score": 29.874,
          "percentage": 0.3237346847597214,
          "label": "Engagement"
        }
      },
      "tier": "legend",
      "percentile": 99.68612680477086,
      "characterClass": "Builder"
    },
    "focusAreas": [
      {
        "tag": "typescript",
        "score": 5458.5,
        "percentage": 30.185976806817568,
        "rank": 2,
        "totalInArea": 717
      },
      {
        "tag": "core",
        "score": 2815,
        "percentage": 15.567193315231556,
        "rank": 1,
        "totalInArea": 318
      },
      {
        "tag": "docs",
        "score": 2395.5,
        "percentage": 13.247322055643762,
        "rank": 2,
        "totalInArea": 612
      }
    ],
    "achievements": [
      {
        "type": "level",
        "tier": "legend",
        "earnedAt": "2026-05-02T23:27:30.440Z"
      },
      {
        "type": "streak",
        "tier": "beginner",
        "earnedAt": "2025-10-27T23:09:13.462Z"
      },
      {
        "type": "pr_master",
        "tier": "legend",
        "earnedAt": "2026-04-12T23:23:19.484Z"
      },
      {
        "type": "bug_hunter",
        "tier": "beginner",
        "earnedAt": "2025-10-27T23:09:13.481Z"
      },
      {
        "type": "review_champion",
        "tier": "elite",
        "earnedAt": "2025-10-27T23:09:13.498Z"
      }
    ],
    "profile": {
      "contributorType": "author",
      "prMergeRate": 64.8,
      "reviewActivity": "high"
    },
    "wallets": {
      "ethereum": "0x1b324Bfc7A0b93D621d8A85F3fF6375528bFae8D",
      "solana": "5rZBMzhX4NiEwSGiJidacmY7HfGWKT41sE1PnpXBSLvG"
    }
  },
  "links": {
    "summaries": {
      "lifetime": "https://elizaOS.github.io/api/summaries/contributors/lalalune/lifetime.json",
      "monthly": "https://elizaOS.github.io/api/summaries/contributors/lalalune/month/latest.json",
      "weekly": "https://elizaOS.github.io/api/summaries/contributors/lalalune/week/latest.json",
      "daily": "https://elizaOS.github.io/api/summaries/contributors/lalalune/day/latest.json"
    },
    "github": "https://github.com/lalalune",
    "profile": "https://elizaOS.github.io/profile/lalalune"
  }
}