{
  "version": "1.0",
  "type": "contributor",
  "interval": "lifetime",
  "date": "2026-01-11",
  "generatedAt": "2026-01-11T02:01:50.152Z",
  "sourceLastUpdated": "2026-01-11T02:01:50.152Z",
  "contentFormat": "markdown",
  "contentHash": "281d06f8924e565d255072f0dfd6a6f5a234fed8a181a066e90f925db19eb71a",
  "entity": {
    "username": "pengqiseven"
  },
  "content": "# pengqiseven\n\n## Activity Ledger\n- **Pull Requests Authored:** 1 merged, 0 open/closed\n- **Pull Requests Reviewed:** 0 total\n- **Issues:** 0 opened, 0 closed\n- **Avg Time to Merge:** 95 hours\n\n## Contribution Domains\n- **Documentation & Code Hygiene:** Addressed minor text corrections within the codebase.\n  - PRs: elizaos/eliza#4615 (chore: fix some typos in comment)"
}