{
  "version": "1.0",
  "username": "digisomni",
  "generatedAt": "2026-01-28T23:18:53.083Z",
  "characterSheet": {
    "tier": "beginner",
    "characterClass": "Builder",
    "percentile": 41.55124653739612,
    "rank": {
      "monthly": 1015,
      "weekly": 999,
      "lifetime": 844
    },
    "scoreBreakdown": {
      "total": 23.04486522358297,
      "distribution": {
        "prs": {
          "score": 23.04486522358297,
          "percentage": 100,
          "label": "Builder"
        },
        "issues": {
          "score": 0,
          "percentage": 0,
          "label": "Hunter"
        },
        "reviews": {
          "score": 0,
          "percentage": 0,
          "label": "Reviews"
        },
        "comments": {
          "score": 0,
          "percentage": 0,
          "label": "Engagement"
        }
      },
      "tier": "beginner",
      "percentile": 41.55124653739612,
      "characterClass": "Builder"
    },
    "focusAreas": [
      {
        "tag": "ui",
        "score": 12.600000000000001,
        "percentage": 42.00000000000001,
        "rank": 37,
        "totalInArea": 67
      },
      {
        "tag": "typescript",
        "score": 9,
        "percentage": 30,
        "rank": 387,
        "totalInArea": 682
      },
      {
        "tag": "react",
        "score": 8.4,
        "percentage": 28.000000000000004,
        "rank": 35,
        "totalInArea": 73
      }
    ],
    "profile": {
      "contributorType": "author",
      "prMergeRate": 100,
      "reviewActivity": "low"
    },
    "wallets": {}
  },
  "links": {
    "summaries": {
      "lifetime": "https://elizaOS.github.io/api/summaries/contributors/digisomni/lifetime.json",
      "monthly": "https://elizaOS.github.io/api/summaries/contributors/digisomni/month/latest.json",
      "weekly": "https://elizaOS.github.io/api/summaries/contributors/digisomni/week/latest.json",
      "daily": "https://elizaOS.github.io/api/summaries/contributors/digisomni/day/latest.json"
    },
    "github": "https://github.com/digisomni",
    "profile": "https://elizaOS.github.io/profile/digisomni"
  }
}